pdqhash/__init__.py
pdqhash/_version.py
pdqhash/bindings.cp313-win_amd64.pyd
pdqhash/bindings.pyx
pdqhash-0.2.8.dist-info/licenses/LICENSE
pdqhash-0.2.8.dist-info/METADATA
pdqhash-0.2.8.dist-info/WHEEL
pdqhash-0.2.8.dist-info/top_level.txt
pdqhash-0.2.8.dist-info/RECORD
