Metadata-Version: 2.4
Name: pdqhash
Version: 0.2.8
Summary: "Python bindings for Facebook's PDQ hash"
Home-page: https://github.com/faustomorales/pdqhash-python
Author: Fausto Morales
Author-email: faustomorales@gmail.com
License: MIT
Classifier: Development Status :: 5 - Production/Stable
Classifier: Programming Language :: Python :: 3
Classifier: Programming Language :: Python :: 3 :: Only
Classifier: Programming Language :: Python :: 3.9
Classifier: Programming Language :: Python :: 3.10
Classifier: Programming Language :: Python :: 3.11
Classifier: Programming Language :: Python :: 3.12
Classifier: Programming Language :: Python :: 3.13
Classifier: Operating System :: POSIX :: Linux
Classifier: Operating System :: Unix
Classifier: Operating System :: MacOS
Classifier: Operating System :: Microsoft :: Windows
License-File: LICENSE
Dynamic: license-file
